chest_simulator/__init__.py
chest_simulator/chests.py
chest_simulator/menu.py
chest_simulator_package-0.0.1.dist-info/LICENSE
chest_simulator_package-0.0.1.dist-info/METADATA
chest_simulator_package-0.0.1.dist-info/WHEEL
chest_simulator_package-0.0.1.dist-info/top_level.txt
chest_simulator_package-0.0.1.dist-info/RECORD
