Metadata-Version: 2.1
Name: chest-simulator-package
Version: 0.0.1
Summary: A random chests simulator
Home-page: https://github.com/henrique-sk/chest_simulator_package
Author: Henrique SK
License-File: LICENSE
Requires-Dist: requests
Requires-Dist: importlib-metadata ; python_version >= "3.5"
